pymcfunc/__init__.py
pymcfunc/advancements.py
pymcfunc/coords.py
pymcfunc/entities.py
pymcfunc/errors.py
pymcfunc/func_handlers.py
pymcfunc/internal.py
pymcfunc/item_modifiers.py
pymcfunc/loot_tables.py
pymcfunc/number_providers.py
pymcfunc/pack.py
pymcfunc/predicates.py
pymcfunc/rawcommands.py
pymcfunc/rawtext.py
pymcfunc/recipes.py
pymcfunc/selectors.py
pymcfunc/variables.py
pymcfunc-0.4.dist-info/LICENSE
pymcfunc-0.4.dist-info/METADATA
pymcfunc-0.4.dist-info/WHEEL
pymcfunc-0.4.dist-info/top_level.txt
pymcfunc-0.4.dist-info/RECORD
