Metadata-Version: 2.1
Name: pymcfunc
Version: 0.4
Summary: Minecraft functions, pythonised
Home-page: https://github.com/iiiii7d/pymcfunc
Author: 7d
Author-email: i.third.7d@protonmail.com
License: gpl-3.0
Download-URL: https://github.com/iiiii7d/pymcfunc/archive/refs/tags/v0.4.tar.gz
Keywords: pymcfunc,minecraft,commands,function
Platform: UNKNOWN
Classifier: Development Status :: 4 - Beta
Classifier: Intended Audience :: Developers
Classifier: License :: OSI Approved :: GNU General Public License v3 (GPLv3)
Classifier: Natural Language :: English
Classifier: Programming Language :: Python
Classifier: Programming Language :: Python :: 3
Classifier: Programming Language :: Python :: 3.6
Classifier: Programming Language :: Python :: 3.7
Classifier: Programming Language :: Python :: 3.8
Classifier: Programming Language :: Python :: 3.9
Classifier: Programming Language :: Python :: 3.10
Classifier: Topic :: Games/Entertainment
Requires-Python: >=3.6
